kaplan/__init__.py
kaplan/kdb.py
kaplan/kxliff.py
kaplan/language_codes.py
kaplan/project.py
kaplan/sdlxliff.py
kaplan/tmx.py
kaplan/tools.py
kaplan/utils.py
kaplan/xliff.py
kaplan-0.16.0.dist-info/LICENSE
kaplan-0.16.0.dist-info/METADATA
kaplan-0.16.0.dist-info/WHEEL
kaplan-0.16.0.dist-info/top_level.txt
kaplan-0.16.0.dist-info/RECORD
