Metadata-Version: 2.1
Name: kaplan
Version: 0.16.0
Summary: A computer-assisted translation tool package
Home-page: https://github.com/kaplanPRO/kaplanpy
Author: Kaplan
Author-email: contact@kaplan.pro
License: UNKNOWN
Project-URL: Kaplan Homepage, https://kaplan.pro
Keywords: CAT,computer-assisted translation,computer-aided translation,translation,free-to-use
Platform: UNKNOWN
Classifier: Development Status :: 4 - Beta
Classifier: Intended Audience :: Developers
Classifier: License :: OSI Approved :: MIT License
Classifier: Operating System :: OS Independent
Classifier: Programming Language :: Python :: 3
License-File: LICENSE
Requires-Dist: lxml
Requires-Dist: regex
